__init__.py
dwhapi/__init__.py
dwhapi/base.py
dwhapi/ddl.py
dwhapi/exceptions.py
dwhapi/project.py
dwhapi/settings.py
dwhapi-0.0.4.dist-info/LICENSE
dwhapi-0.0.4.dist-info/METADATA
dwhapi-0.0.4.dist-info/WHEEL
dwhapi-0.0.4.dist-info/top_level.txt
dwhapi-0.0.4.dist-info/RECORD
