Metadata-Version: 2.1
Name: dwhapi
Version: 0.0.4
Summary: whl api
Author-email: Evgeniy Ilichev <developer@example.com>
Project-URL: Homepage, https://github.com/pypa/sampleproject
Project-URL: Bug Tracker, https://github.com/pypa/sampleproject/issues
Classifier: Programming Language :: Python :: 3
Classifier: License :: OSI Approved :: MIT License
Classifier: Operating System :: OS Independent
Requires-Python: >=3.7
License-File: LICENSE
Requires-Dist: feedparser (>=5.2.0)
Requires-Dist: requests (>=2.28.1)
